CHANGELOG.txt
MANIFEST.in
Preprocessing.py
README.txt
__init__.py
_all_in_one.py
actvfn.py
dense.py
license.txt
loss.py
main.py
metrics.py
model.py
saver.py
setup.py
viz.py
mydemo.egg-info/SOURCES.txt
mydemo.egg-info/dependency_links.txt
mydemo.egg-info/top_level.txt
passant.egg-info/PKG-INFO
passant.egg-info/SOURCES.txt
passant.egg-info/dependency_links.txt
passant.egg-info/top_level.txt